{"_ts":[1588299418,1588347055,1588398408,1588552304,1588649503,1588698237,1588741855,1588785395,1588833096,1588879847,1588932989,1589033734,1589126671,1589218306],"_r":{"breakdown":{"html":{"bytes":[0,0,0,0,0,0,0,0,0,0,0,0,0,0],"requests":[0,0,0,0,0,0,0,0,0,0,0,0,0,0]},"js":{"bytes":[0,0,0,0,0,0,0,0,0,0,0,0,0,0],"requests":[0,0,0,0,0,0,0,0,0,0,0,0,0,0]},"css":{"bytes":[0,0,0,0,0,0,0,0,0,0,0,0,0,0],"requests":[0,0,0,0,0,0,0,0,0,0,0,0,0,0]},"image":{"bytes":[0,0,0,0,0,0,0,0,0,0,0,0,0,0],"requests":[0,0,0,0,0,0,0,0,0,0,0,0,0,0]},"flash":{"bytes":[0,0,0,0,0,0,0,0,0,0,0,0,0,0],"requests":[0,0,0,0,0,0,0,0,0,0,0,0,0,0]},"font":{"bytes":[0,0,0,0,0,0,0,0,0,0,0,0,0,0],"requests":[0,0,0,0,0,0,0,0,0,0,0,0,0,0]},"video":{"bytes":[0,0,0,0,0,0,0,0,0,0,0,0,0,0],"requests":[0,0,0,0,0,0,0,0,0,0,0,0,0,0]},"other":{"bytes":[2962,2962,2962,2962,2962,2962,2962,2962,2962,2962,2962,2962,2962,2962],"requests":[2,2,2,2,2,2,2,2,2,2,2,2,2,2]}},"date":[1588299418,1588347055,1588398408,1588552304,1588649503,1588698237,1588741855,1588785395,1588833096,1588879847,1588932989,1589033734,1589126671,1589218306],"domElements":[null,null,null,null,null,null,null,null,null,null,null,null,null,null],"domInteractive":[null,null,null,null,null,null,null,null,null,null,null,null,null,null],"firstPaint":[null,null,null,null,null,null,null,null,null,null,null,null,null,null],"fullyLoaded":[null,null,null,null,null,null,null,null,null,null,null,null,null,null],"id":["200501_N2_8ed1763ace06563ac3cf5cb14247413c","200501_X4_aa8cbbd979dca4d43870a25b4e7326cd","200502_1P_5b8cd6df8dd0ede0722818f8ceaabd43","200504_QW_81d6efb8d95f6b30a71303a23460d6fc","200505_AG_a7fbb44e2656a4e310892c1e2c67a251","200505_FV_f48638ea687df100ab0a59d4d955a940","200506_MT_4bbea15d68beec7811556ac5ca421d16","200506_DP_d55ccc0d88e96830b41465036641b580","200507_KS_d012875f9ff06af354cde534883e9204","200507_KC_80478e1e50e3071290a0c4c3eda5b2ec","200508_7E_de758f7cac1228b24afb7a9784de4030","200509_KB_a3f106881bcc8efc50011a6aca3b4c50","200510_YR_fad169bd520a89be1f6328d8b09db89b","200511_JP_4b22a0371837ab4be44568607666d59f"],"loadTime":[null,null,null,null,null,null,null,null,null,null,null,null,null,null],"render":[null,null,null,null,null,null,null,null,null,null,null,null,null,null],"SpeedIndex":[null,null,null,null,null,null,null,null,null,null,null,null,null,null],"TTFB":[null,null,null,null,null,null,null,null,null,null,null,null,null,null],"videoFrames":[[{"_i":"ms_000000.jpg","_t":0,"_vc":100}],[{"_i":"ms_000000.jpg","_t":0,"_vc":100}],[{"_i":"ms_000000.jpg","_t":0,"_vc":100}],[{"_i":"ms_000000.jpg","_t":0,"_vc":100}],[{"_i":"ms_000000.jpg","_t":0,"_vc":100}],[{"_i":"ms_000000.jpg","_t":0,"_vc":100}],[{"_i":"ms_000000.jpg","_t":0,"_vc":100}],[{"_i":"ms_000000.jpg","_t":0,"_vc":100}],[{"_i":"ms_000000.jpg","_t":0,"_vc":100}],[{"_i":"ms_000000.jpg","_t":0,"_vc":100}],[{"_i":"ms_000000.jpg","_t":0,"_vc":100}],[{"_i":"ms_000000.jpg","_t":0,"_vc":100}],[{"_i":"ms_000000.jpg","_t":0,"_vc":100}],[{"_i":"ms_000000.jpg","_t":0,"_vc":100}]],"visualComplete":[null,null,null,null,null,null,null,null,null,null,null,null,null,null],"lighthouse":[null,null,null,null,null,null,null,null,null,null,null,null,null,null],"pagespeed":[67,67,67,66,67,67,65,67,66,67,65,66,67,67]}}